dmmf/__init__.py
dmmf-0.1.dist-info/METADATA
dmmf-0.1.dist-info/WHEEL
dmmf-0.1.dist-info/top_level.txt
dmmf-0.1.dist-info/RECORD
