Metadata-Version: 2.1
Name: dmmf
Version: 0.1
Summary: Model Management
Home-page: https://github.com/Direct-Line-Group/darwin-ds-dmmf-stub
Author: Yuriy Akopov
Author-email: yuriy.akopov@directlinegroup.co.uk
License: UNKNOWN
Platform: UNKNOWN
